vertex_protocol/__init__.py
vertex_protocol/client/__init__.py
vertex_protocol/client/apis/__init__.py
vertex_protocol/client/apis/base.py
vertex_protocol/client/apis/market/__init__.py
vertex_protocol/client/apis/market/execute.py
vertex_protocol/client/apis/market/query.py
vertex_protocol/client/apis/perp/__init__.py
vertex_protocol/client/apis/perp/query.py
vertex_protocol/client/apis/rewards/__init__.py
vertex_protocol/client/apis/rewards/execute.py
vertex_protocol/client/apis/rewards/query.py
vertex_protocol/client/apis/spot/__init__.py
vertex_protocol/client/apis/spot/base.py
vertex_protocol/client/apis/spot/execute.py
vertex_protocol/client/apis/spot/query.py
vertex_protocol/client/apis/subaccount/__init__.py
vertex_protocol/client/apis/subaccount/execute.py
vertex_protocol/client/apis/subaccount/query.py
vertex_protocol/client/context.py
vertex_protocol/contracts/__init__.py
vertex_protocol/contracts/abis/Endpoint.json
vertex_protocol/contracts/abis/FQuerier.json
vertex_protocol/contracts/abis/IClearinghouse.json
vertex_protocol/contracts/abis/IERC20.json
vertex_protocol/contracts/abis/IEndpoint.json
vertex_protocol/contracts/abis/IFoundationRewardsAirdrop.json
vertex_protocol/contracts/abis/IOffchainBook.json
vertex_protocol/contracts/abis/IPerpEngine.json
vertex_protocol/contracts/abis/IProductEngine.json
vertex_protocol/contracts/abis/ISpotEngine.json
vertex_protocol/contracts/abis/IStaking.json
vertex_protocol/contracts/abis/IVrtxAirdrop.json
vertex_protocol/contracts/abis/MockERC20.json
vertex_protocol/contracts/deployments/deployment.abstractMainnet.json
vertex_protocol/contracts/deployments/deployment.abstractTestnet.json
vertex_protocol/contracts/deployments/deployment.arbitrumOne.json
vertex_protocol/contracts/deployments/deployment.arbitrumSepolia.json
vertex_protocol/contracts/deployments/deployment.baseMainnet.json
vertex_protocol/contracts/deployments/deployment.baseTestnet.json
vertex_protocol/contracts/deployments/deployment.beraMainnet.json
vertex_protocol-3.2.1.dist-info/METADATA
vertex_protocol-3.2.1.dist-info/WHEEL
vertex_protocol-3.2.1.dist-info/entry_points.txt
vertex_protocol-3.2.1.dist-info/RECORD
