Metadata-Version: 2.3
Name: vertex-protocol
Version: 3.2.1
Summary: Vertex Protocol SDK
Keywords: vertex protocol,vertex sdk,vertex protocol api
Author: Jeury Mejia
Author-email: jeury@vertexprotocol.com
Maintainer: Frank Jia
Maintainer-email: frank@vertexprotocol.com
Requires-Python: >=3.9,<4.0
Classifier: Programming Language :: Python :: 3
Classifier: Programming Language :: Python :: 3.9
Classifier: Programming Language :: Python :: 3.10
Classifier: Programming Language :: Python :: 3.11
Classifier: Programming Language :: Python :: 3.12
Classifier: Programming Language :: Python :: 3.13
Requires-Dist: eth-account (>=0.8.0,<0.9.0)
Requires-Dist: pydantic (>=1.10.7,<2.0.0)
Requires-Dist: web3 (>=6.4.0,<7.0.0)
Project-URL: Documentation, https://vertex-protocol.github.io/vertex-python-sdk/
Project-URL: Homepage, https://vertexprotocol.com/
